dotflow_mongodb/__init__.py
dotflow_mongodb/main.py
dotflow_mongodb-0.1.2.dist-info/LICENSE
dotflow_mongodb-0.1.2.dist-info/METADATA
dotflow_mongodb-0.1.2.dist-info/WHEEL
dotflow_mongodb-0.1.2.dist-info/RECORD
