Metadata-Version: 2.3
Name: dotflow_mongodb
Version: 0.1.2
Summary: Dotflow Storage MongoDB
License: MIT License
Author: Fernando Celmer
Author-email: email@fernandocelmer.com
Requires-Python: >=3.9
Classifier: Development Status :: 4 - Beta
Classifier: Operating System :: OS Independent
Classifier: Intended Audience :: Developers
Classifier: Natural Language :: English
Classifier: Programming Language :: Python :: 3.9
Classifier: Programming Language :: Python :: 3.10
Classifier: Programming Language :: Python :: 3.11
Classifier: Programming Language :: Python :: 3.12
Requires-Dist: dotflow
Requires-Dist: pymongo
Project-URL: Documentation, https://github.com/dotflow-io/dotflow-mongodb/blob/master/README.md
Project-URL: Homepage, https://github.com/dotflow-io/dotflow-mongodb
Project-URL: Issues, https://github.com/dotflow-io/dotflow-mongodb/issues
Project-URL: Repository, https://github.com/dotflow-io/dotflow-mongodb
